Linkify/__init__.py
Linkify/linkedlist.py
tests/__init__.py
tests/test_linkedlist.py
Linkify_Linkedlist-0.1.2.dist-info/LICENSE.txt
Linkify_Linkedlist-0.1.2.dist-info/METADATA
Linkify_Linkedlist-0.1.2.dist-info/WHEEL
Linkify_Linkedlist-0.1.2.dist-info/top_level.txt
Linkify_Linkedlist-0.1.2.dist-info/RECORD
