Metadata-Version: 2.1
Name: Linkify-Linkedlist
Version: 0.1.2
Summary: A Python library to convert arrays to linked lists
Home-page: https://github.com/Shankhosuvro-G/linkify
Author: Shankhosuvro Ghosh
Author-email: shankhosuvro.ghosh@gmail.com
Classifier: Programming Language :: Python :: 3
Classifier: License :: OSI Approved :: MIT License
Classifier: Operating System :: OS Independent
Requires-Python: >=3.6
License-File: LICENSE.txt
